ecnu_network_login/__init__.py
ecnu_network_login/login.py
ecnu_network_login/utils/__init__.py
ecnu_network_login/utils/encryption.js
ecnu_network_login/utils/encryption.py
ecnu_network_login/utils/misc.py
ecnu_network_login/utils/network.py
ecnu_network_login-1.1.dist-info/LICENSE
ecnu_network_login-1.1.dist-info/METADATA
ecnu_network_login-1.1.dist-info/WHEEL
ecnu_network_login-1.1.dist-info/entry_points.txt
ecnu_network_login-1.1.dist-info/top_level.txt
ecnu_network_login-1.1.dist-info/RECORD
