Metadata-Version: 2.1
Name: ecnu_network_login
Version: 1.1
Summary: ecnu network login
Author: ccjiahao
Author-email: jhchao502@163.com
Requires-Python: >=3.7.3
License-File: LICENSE
Requires-Dist: requests ==2.31.0
Requires-Dist: urllib3 ==1.26.18
Requires-Dist: js2py ==0.74
